pytomutil/SRGBColor.py
pytomutil/__init__.py
pytomutil/all.py
pytomutil/balanced.py
pytomutil/dicts.py
pytomutil/file.py
pytomutil/frange.py
pytomutil/graph.py
pytomutil/meta.py
pytomutil/numeric.py
pytomutil/vec.py
pytomutil_elunico-0.0.13.dist-info/licenses/LICENSE
pytomutil_elunico-0.0.13.dist-info/METADATA
pytomutil_elunico-0.0.13.dist-info/WHEEL
pytomutil_elunico-0.0.13.dist-info/top_level.txt
pytomutil_elunico-0.0.13.dist-info/RECORD
