Metadata-Version: 2.4
Name: pytomutil-elunico
Version: 0.0.13
Summary: Library for parsing and writing Simple Property List (SPL) files 
Home-page: https://github.com/elunico/pytomutil
Author: Thomas Povinelli
Author-email: tompov227@gmail.com
Classifier: Programming Language :: Python :: 3
Classifier: License :: OSI Approved :: MIT License
Classifier: Operating System :: OS Independent
Requires-Python: >=3.10
License-File: LICENSE
Dynamic: author
Dynamic: author-email
Dynamic: classifier
Dynamic: description
Dynamic: description-content-type
Dynamic: home-page
Dynamic: license-file
Dynamic: requires-python
Dynamic: summary
